pudim_hunter_driver/__init__.py
pudim_hunter_driver/_version.py
pudim_hunter_driver/driver.py
pudim_hunter_driver/exceptions.py
pudim_hunter_driver/models.py
pudim_hunter_driver-1.0.0.dist-info/LICENSE.md
pudim_hunter_driver-1.0.0.dist-info/METADATA
pudim_hunter_driver-1.0.0.dist-info/WHEEL
pudim_hunter_driver-1.0.0.dist-info/top_level.txt
pudim_hunter_driver-1.0.0.dist-info/RECORD
