Metadata-Version: 2.1
Name: pudim-hunter-driver
Version: 1.0.0
Summary: Common interface for implementing job search drivers for The Pudim Hunter platform
Author-email: The Pudim Hunter Team <luis.reis@gmail.com>
License: MIT
Project-URL: Source, https://github.com/luismr/pudim-hunter-driver
Project-URL: Bug Tracker, https://github.com/luismr/pudim-hunter-driver/issues
Classifier: Development Status :: 3 - Alpha
Classifier: Intended Audience :: Developers
Classifier: Operating System :: OS Independent
Classifier: Programming Language :: Python :: 3
Classifier: Programming Language :: Python :: 3.9
Classifier: Topic :: Software Development :: Libraries :: Python Modules
Requires-Python: >=3.9
License-File: LICENSE.md
Requires-Dist: pydantic>=2.5.0
Requires-Dist: python-dateutil>=2.8.2
Requires-Dist: typing-extensions>=4.8.0
Requires-Dist: pytest>=7.4.0
Requires-Dist: pytest-asyncio>=0.21.0
Requires-Dist: pytest-cov>=4.1.0
Requires-Dist: setuptools==69.2.0
Requires-Dist: wheel
Requires-Dist: twine
Requires-Dist: setuptools-scm>=8.0.0
